{
    "lrk_id": "108757420",
    "type_oko": "VGO",
    "opc": "Nee",
    "actuele_naam_oko": "Gijsbrechts- van Gestel",
    "aantal_kindplaatsen": 6,
    "status": "Ingeschreven",
    "inschrijfdatum": "16-09-2010",
    "opvanglocatie_adres": "Kerksingel 12 ",
    "opvanglocatie_postcode": "5087BT",
    "opvanglocatie_woonplaats": "Diessen",
    "bag_id": "0798010000003385",
    "naam_houder": "Gijsbrechts-van Gestel",
    "contact_telefoon": "''",
    "cbs_code": "798",
    "verantwoordelijke_gemeente": "Hilvarenbeek",
    "gastouderbureau_1": "561668085",
    "gastouderbureau_2": "590085931",
    "lrk_url": "https://www.landelijkregisterkinderopvang.nl/pp/#/inzien/oko/gegevens/6c2e8c84-cb1c-43f9-ab21-0f9ed087afea"
}
