{
    "lrk_id": "113032006",
    "type_oko": "VGO",
    "opc": "Nee",
    "actuele_naam_oko": "J.J. Horck Lichtenberg",
    "aantal_kindplaatsen": 6,
    "status": "Ingeschreven",
    "inschrijfdatum": "07-03-2022",
    "opvanglocatie_adres": "Opvang bij de vraagouder",
    "naam_houder": "Horck Lichtenberg",
    "contact_telefoon": "''",
    "cbs_code": "158",
    "verantwoordelijke_gemeente": "Haaksbergen",
    "gastouderbureau_1": "225000520",
    "lrk_url": "https://www.landelijkregisterkinderopvang.nl/pp/#/inzien/oko/gegevens/cd8238b0-29f2-47de-b180-51ef9d96dc2b"
}
