{
    "lrk_id": "147555115",
    "type_oko": "KDV",
    "opc": "Nee",
    "actuele_naam_oko": "KDV de Brink",
    "aantal_kindplaatsen": 97,
    "ve": "Nee",
    "status": "Ingeschreven",
    "inschrijfdatum": "05-09-2012",
    "opvanglocatie_adres": "Kastanjelaan 6 ",
    "opvanglocatie_postcode": "2351ND",
    "opvanglocatie_woonplaats": "Leiderdorp",
    "bag_id": "0547010000323471",
    "naam_houder": "FloreoKids",
    "kvk_nummer_houder": "41165967",
    "vestigingsnummer_houder": "000041165967",
    "rechtsvorm_houder": "Stichting",
    "start_geschillencommissie": "2016-01-18",
    "houder_adres": "Postbus 9",
    "houder_postcode": "2350AA",
    "houder_woonplaats": "Leiderdorp",
    "correspondentie_adres": "Postbus 9",
    "correspondentie_postcode": "2350AA",
    "correspondentie_woonplaats": "LEIDERDORP",
    "contact_persoon": "FloreoKids",
    "contact_telefoon": "'071-5817777'",
    "contact_emailadres": "info@floreokids.nl",
    "contact_website": "http://www.floreokids.nl",
    "cbs_code": "547",
    "verantwoordelijke_gemeente": "Leiderdorp",
    "lrk_url": "https://www.landelijkregisterkinderopvang.nl/pp/#/inzien/oko/gegevens/6add4af1-0b41-449e-adbe-b9a055c5efcc"
}
