{
    "lrk_id": "151387576",
    "type_oko": "VGO",
    "opc": "Nee",
    "actuele_naam_oko": "Zaal",
    "aantal_kindplaatsen": 6,
    "status": "Ingeschreven",
    "inschrijfdatum": "28-12-2022",
    "opvanglocatie_adres": "Opvang bij de vraagouder",
    "naam_houder": "Zaal",
    "contact_telefoon": "''",
    "cbs_code": "518",
    "verantwoordelijke_gemeente": "'s-Gravenhage",
    "gastouderbureau_1": "171802093",
    "lrk_url": "https://www.landelijkregisterkinderopvang.nl/pp/#/inzien/oko/gegevens/f2695bc0-09aa-4ed8-bcce-91330c36506d"
}
