{
    "lrk_id": "195319564",
    "type_oko": "VGO",
    "opc": "Nee",
    "actuele_naam_oko": "Oudheusden-de Heer",
    "aantal_kindplaatsen": 6,
    "status": "Ingeschreven",
    "inschrijfdatum": "30-03-2021",
    "opvanglocatie_adres": "Beurtschipperserf 11 ",
    "opvanglocatie_postcode": "3991KM",
    "opvanglocatie_woonplaats": "Houten",
    "bag_id": "0321010000004014",
    "naam_houder": "Oudheusden-de Heer",
    "contact_telefoon": "''",
    "cbs_code": "321",
    "verantwoordelijke_gemeente": "Houten",
    "gastouderbureau_1": "576811993",
    "lrk_url": "https://www.landelijkregisterkinderopvang.nl/pp/#/inzien/oko/gegevens/4772611b-78cd-424d-ac8a-bb25a8333181"
}
