{
    "lrk_id": "279119781",
    "type_oko": "BSO",
    "opc": "Nee",
    "actuele_naam_oko": "Nijnsel BSO",
    "aantal_kindplaatsen": 40,
    "status": "Ingeschreven",
    "inschrijfdatum": "01-08-2017",
    "opvanglocatie_adres": "Jasmijnstraat 11A ",
    "opvanglocatie_postcode": "5492JS",
    "opvanglocatie_woonplaats": "Sint-Oedenrode",
    "bag_id": "1948010040630735",
    "naam_houder": "De Verbinding B.V.",
    "kvk_nummer_houder": "50168223",
    "vestigingsnummer_houder": "000037672800",
    "rechtsvorm_houder": "BV",
    "start_geschillencommissie": "2016-01-25",
    "houder_adres": "Pearl S. Buckstraat 1 ",
    "houder_postcode": "5491DG",
    "houder_woonplaats": "Sint-Oedenrode",
    "contact_persoon": "P.A. van der Kruis",
    "contact_telefoon": "'0413-782142'",
    "contact_emailadres": "administratie@deverbinding-sintoedenrode.nl",
    "contact_website": "http://www.deverbinding-sintoedenrode.nl",
    "cbs_code": "1948",
    "verantwoordelijke_gemeente": "Meierijstad",
    "lrk_url": "https://www.landelijkregisterkinderopvang.nl/pp/#/inzien/oko/gegevens/fec08798-495f-490f-b5b5-35860e4e58e5"
}
