{
    "lrk_id": "687466878",
    "type_oko": "BSO",
    "opc": "Nee",
    "actuele_naam_oko": "Babbels bso locatie de Carrousel",
    "aantal_kindplaatsen": 22,
    "status": "Ingeschreven",
    "inschrijfdatum": "22-03-2018",
    "opvanglocatie_adres": "Smaragd 27 ",
    "opvanglocatie_postcode": "1703GA",
    "opvanglocatie_woonplaats": "Heerhugowaard",
    "bag_id": "0398010000010651",
    "naam_houder": "Babbels Scholen BV",
    "kvk_nummer_houder": "52694801",
    "vestigingsnummer_houder": "000022612459",
    "rechtsvorm_houder": "BV",
    "start_geschillencommissie": "2016-03-09",
    "houder_adres": "W.M. Dudokweg 67 ",
    "houder_postcode": "1703DC",
    "houder_woonplaats": "Heerhugowaard",
    "contact_persoon": "Meghan Tsjerkstra",
    "contact_telefoon": "'06-19170592'",
    "contact_emailadres": "info@kinderopvangbabbels.nl",
    "contact_website": "http://www.kinderopvangbabbels.nl",
    "cbs_code": "1980",
    "verantwoordelijke_gemeente": "Dijk en Waard",
    "lrk_url": "https://www.landelijkregisterkinderopvang.nl/pp/#/inzien/oko/gegevens/bc0c22bd-33ee-4145-a8e0-3abb02cb5451"
}
