{
    "lrk_id": "119636049",
    "type_oko": "VGO",
    "opc": "Nee",
    "actuele_naam_oko": "Meer",
    "aantal_kindplaatsen": 6,
    "status": "Ingeschreven",
    "inschrijfdatum": "22-10-2021",
    "opvanglocatie_adres": "Buizerdweide 12 ",
    "opvanglocatie_postcode": "2643LW",
    "opvanglocatie_woonplaats": "Pijnacker",
    "bag_id": "1926010000549549",
    "naam_houder": "Meer",
    "contact_telefoon": "''",
    "cbs_code": "1926",
    "verantwoordelijke_gemeente": "Pijnacker-Nootdorp",
    "gastouderbureau_1": "121964334",
    "lrk_url": "https://www.landelijkregisterkinderopvang.nl/pp/#/inzien/oko/gegevens/4ef1ef2a-13fd-4393-91d6-ea1cb33dc424"
}
