{
    "lrk_id": "141240672",
    "type_oko": "KDV",
    "opc": "Nee",
    "actuele_naam_oko": "De Polderkids",
    "aantal_kindplaatsen": 16,
    "ve": "Ja",
    "status": "Ingeschreven",
    "inschrijfdatum": "09-01-2024",
    "opvanglocatie_adres": "Heer Willem van Egmondstraat 1 ",
    "opvanglocatie_postcode": "3415PW",
    "opvanglocatie_woonplaats": "Polsbroek",
    "bag_id": "0331010000268280",
    "naam_houder": "Stichting Waardse Kids Peuteropvang",
    "kvk_nummer_houder": "77000633",
    "rechtsvorm_houder": "Onbekend",
    "start_geschillencommissie": "2020-08-18",
    "houder_adres": "Meidoornstraat 3e ",
    "houder_postcode": "2861VH",
    "houder_woonplaats": "Bergambacht",
    "contact_persoon": "Ellen Brouwer",
    "contact_telefoon": "'0182387474'",
    "contact_emailadres": "info@waardsekids.nl",
    "contact_website": "http://www.waardsekids.nl",
    "cbs_code": "331",
    "verantwoordelijke_gemeente": "Lopik",
    "lrk_url": "https://www.landelijkregisterkinderopvang.nl/pp/#/inzien/oko/gegevens/545e5e3f-bb8c-4c70-a5de-f57de38accae"
}
