{
    "lrk_id": "141917386",
    "type_oko": "VGO",
    "opc": "Nee",
    "actuele_naam_oko": "Dekker Balvers",
    "aantal_kindplaatsen": 6,
    "status": "Ingeschreven",
    "inschrijfdatum": "01-07-2016",
    "opvanglocatie_adres": "Falstaffstraat 21 ",
    "opvanglocatie_postcode": "1827RP",
    "opvanglocatie_woonplaats": "Alkmaar",
    "bag_id": "0361010000009056",
    "naam_houder": "Dekker Balvers",
    "contact_telefoon": "''",
    "cbs_code": "361",
    "verantwoordelijke_gemeente": "Alkmaar",
    "gastouderbureau_1": "429285814",
    "lrk_url": "https://www.landelijkregisterkinderopvang.nl/pp/#/inzien/oko/gegevens/69467765-3bfb-40ab-b95f-17d151772dc7"
}
