{
    "lrk_id": "171553238",
    "type_oko": "BSO",
    "opc": "Nee",
    "actuele_naam_oko": "Partou BSO Eva Besnyostraat 491 (IKC Laterna Magica)",
    "aantal_kindplaatsen": 270,
    "status": "Ingeschreven",
    "inschrijfdatum": "26-10-2011",
    "opvanglocatie_adres": "Eva Besnyöstraat 491 ",
    "opvanglocatie_postcode": "1087LG",
    "opvanglocatie_woonplaats": "Amsterdam",
    "bag_id": "0363010011942536",
    "naam_houder": "Partou B.V.",
    "kvk_nummer_houder": "30225440",
    "vestigingsnummer_houder": "000023536691",
    "rechtsvorm_houder": "Besloten Vennootschap",
    "start_geschillencommissie": "2015-12-29",
    "houder_adres": "Postbus 396",
    "houder_postcode": "4130EJ",
    "houder_woonplaats": "Vianen",
    "contact_persoon": "Secretariaat",
    "contact_telefoon": "'088-2357550'",
    "contact_emailadres": "regiosecretariaat@partou.nl",
    "contact_website": "http://www.partou.nl",
    "cbs_code": "363",
    "verantwoordelijke_gemeente": "Amsterdam",
    "lrk_url": "https://www.landelijkregisterkinderopvang.nl/pp/#/inzien/oko/gegevens/30b9fb84-f899-4cdb-a4e8-e1bd956133b1"
}
