{
    "lrk_id": "172044716",
    "type_oko": "VGO",
    "opc": "Nee",
    "actuele_naam_oko": "E. Oude Luttikhuis-Weijermars",
    "aantal_kindplaatsen": 6,
    "status": "Ingeschreven",
    "inschrijfdatum": "03-10-2011",
    "opvanglocatie_adres": "Opvang bij de vraagouder",
    "naam_houder": "Oude Luttikhuis-Weijermars",
    "contact_telefoon": "''",
    "cbs_code": "163",
    "verantwoordelijke_gemeente": "Hellendoorn",
    "gastouderbureau_1": "819651758",
    "lrk_url": "https://www.landelijkregisterkinderopvang.nl/pp/#/inzien/oko/gegevens/d08863a8-8a13-4ffc-b8a3-d39aef978f56"
}
