{
    "lrk_id": "186741030",
    "type_oko": "VGO",
    "opc": "Nee",
    "actuele_naam_oko": "Trommelen",
    "aantal_kindplaatsen": 6,
    "status": "Ingeschreven",
    "inschrijfdatum": "01-03-2021",
    "opvanglocatie_adres": "De Poelsnip 1 ",
    "opvanglocatie_postcode": "1509ZV",
    "opvanglocatie_woonplaats": "Zaandam",
    "bag_id": "0479010000025100",
    "naam_houder": "Trommelen",
    "contact_persoon": "K.J. van Kessel",
    "contact_telefoon": "'0638744732'",
    "contact_emailadres": "info@loky.nl",
    "contact_website": "http://www.loky.nl",
    "cbs_code": "479",
    "verantwoordelijke_gemeente": "Zaanstad",
    "gastouderbureau_1": "376815279",
    "lrk_url": "https://www.landelijkregisterkinderopvang.nl/pp/#/inzien/oko/gegevens/b0c26acf-d0b5-40f7-930d-2b46786ff8d6"
}
