{
    "lrk_id": "230820840",
    "type_oko": "GOB",
    "opc": "Nee",
    "actuele_naam_oko": "Gastouderbureau ViaViela Purmerend",
    "status": "Ingeschreven",
    "inschrijfdatum": "01-01-2010",
    "opvanglocatie_adres": "De Vooruitgang 51 ",
    "opvanglocatie_postcode": "1693DT",
    "opvanglocatie_woonplaats": "Wervershoof",
    "bag_id": "0459010000000562",
    "naam_houder": "Laan",
    "kvk_nummer_houder": "77154673",
    "vestigingsnummer_houder": "000002532220",
    "rechtsvorm_houder": "Eenmanszaak",
    "start_geschillencommissie": "2020-02-07",
    "correspondentie_adres": "De Vooruitgang 51 ",
    "correspondentie_postcode": "1693DT",
    "correspondentie_woonplaats": "Wervershoof",
    "contact_persoon": "Sandy Laan",
    "contact_telefoon": "'06-17241729'",
    "contact_emailadres": "sandy.laan@viaviela.nl",
    "contact_website": "http://www.viaviela.nl",
    "cbs_code": "420",
    "verantwoordelijke_gemeente": "Medemblik",
    "lrk_url": "https://www.landelijkregisterkinderopvang.nl/pp/#/inzien/oko/gegevens/ffef7862-defe-4ae2-8db1-3fe8f918edda"
}
