{
    "lrk_id": "265802489",
    "type_oko": "VGO",
    "opc": "Nee",
    "actuele_naam_oko": "Goedhart Bruins",
    "aantal_kindplaatsen": 6,
    "status": "Ingeschreven",
    "inschrijfdatum": "05-11-2018",
    "opvanglocatie_adres": "Opvang bij de vraagouder",
    "naam_houder": "Goedhart Bruins",
    "contact_telefoon": "''",
    "cbs_code": "193",
    "verantwoordelijke_gemeente": "Zwolle",
    "gastouderbureau_1": "140767186",
    "lrk_url": "https://www.landelijkregisterkinderopvang.nl/pp/#/inzien/oko/gegevens/f6f5b567-bb0e-472b-81d8-bff20eea56ae"
}
