{
    "lrk_id": "289853990",
    "type_oko": "VGO",
    "opc": "Nee",
    "actuele_naam_oko": "Jubbega",
    "aantal_kindplaatsen": 6,
    "status": "Ingeschreven",
    "inschrijfdatum": "26-09-2023",
    "opvanglocatie_adres": "Opvang bij de vraagouder",
    "naam_houder": "Jubbega",
    "contact_telefoon": "''",
    "cbs_code": "373",
    "verantwoordelijke_gemeente": "Bergen (NH)",
    "gastouderbureau_1": "766604895",
    "lrk_url": "https://www.landelijkregisterkinderopvang.nl/pp/#/inzien/oko/gegevens/e09a2232-e60f-4a62-ae21-ac848b26b9d2"
}
