{
    "lrk_id": "314252149",
    "type_oko": "VGO",
    "opc": "Nee",
    "actuele_naam_oko": "Renkema",
    "aantal_kindplaatsen": 6,
    "status": "Ingeschreven",
    "inschrijfdatum": "10-01-2022",
    "opvanglocatie_adres": "Opvang bij de vraagouder",
    "naam_houder": "Renkema",
    "contact_persoon": "Gastouderbureau Jool",
    "contact_telefoon": "'0622685429'",
    "contact_emailadres": "alina.bruining@gobjool.nl",
    "cbs_code": "90",
    "verantwoordelijke_gemeente": "Smallingerland",
    "gastouderbureau_1": "191971868",
    "lrk_url": "https://www.landelijkregisterkinderopvang.nl/pp/#/inzien/oko/gegevens/73e68a7d-ab1e-4cd2-b8c2-ee38c888be91"
}
