{
    "lrk_id": "528648664",
    "type_oko": "KDV",
    "opc": "Nee",
    "actuele_naam_oko": "Kibeo De Hoeksteen Oud-Beijerland",
    "aantal_kindplaatsen": 31,
    "ve": "Nee",
    "status": "Ingeschreven",
    "inschrijfdatum": "14-05-2012",
    "opvanglocatie_adres": "Aalscholver 2 ",
    "opvanglocatie_postcode": "3263BA",
    "opvanglocatie_woonplaats": "Oud-Beijerland",
    "bag_id": "0584010001295811",
    "naam_houder": "Stichting Kibeo",
    "kvk_nummer_houder": "22049355",
    "vestigingsnummer_houder": "000058453474",
    "rechtsvorm_houder": "Stichting",
    "start_geschillencommissie": "2016-01-25",
    "houder_adres": "Postbus 328",
    "houder_postcode": "4460AS",
    "houder_woonplaats": "Goes",
    "correspondentie_adres": "Stationspark 2 ",
    "correspondentie_postcode": "4462DZ",
    "correspondentie_woonplaats": "Goes",
    "contact_persoon": "Afdeling Facilitair",
    "contact_telefoon": "'0113-760200'",
    "contact_emailadres": "info@kibeo.nl",
    "contact_website": "http://www.kibeo.nl",
    "cbs_code": "1963",
    "verantwoordelijke_gemeente": "Hoeksche Waard",
    "lrk_url": "https://www.landelijkregisterkinderopvang.nl/pp/#/inzien/oko/gegevens/f36da991-af14-4083-8b1e-583d967b2f75"
}
