{
    "lrk_id": "659363653",
    "type_oko": "KDV",
    "opc": "Nee",
    "actuele_naam_oko": "Kids Society Erica locatie Jacob Catsstraat",
    "aantal_kindplaatsen": 94,
    "ve": "Ja",
    "status": "Ingeschreven",
    "inschrijfdatum": "20-12-2010",
    "opvanglocatie_adres": "Jacob Catsstraat 1 ",
    "opvanglocatie_postcode": "5671VP",
    "opvanglocatie_woonplaats": "Nuenen",
    "bag_id": "0820010000035918",
    "naam_houder": "Stichting Kinderopvang Erica",
    "kvk_nummer_houder": "41088689",
    "rechtsvorm_houder": "Stichting",
    "start_geschillencommissie": "2015-12-23",
    "houder_adres": "Jacob Catsstraat 1 ",
    "houder_postcode": "5671VP",
    "houder_woonplaats": "Nuenen",
    "correspondentie_adres": "Postbus 60",
    "correspondentie_postcode": "5670AB",
    "correspondentie_woonplaats": "NUENEN",
    "contact_persoon": "M.F.M. Strolenberg",
    "contact_telefoon": "'040-2635155'",
    "contact_emailadres": "m.strolenberg@kidssociety.nl",
    "contact_website": "http://www.kidssociety.nl",
    "cbs_code": "820",
    "verantwoordelijke_gemeente": "Nuenen c.a.",
    "lrk_url": "https://www.landelijkregisterkinderopvang.nl/pp/#/inzien/oko/gegevens/026cff7d-79eb-41fd-97f0-ab98a5451eb8"
}
