{
    "lrk_id": "103313229",
    "type_oko": "BSO",
    "opc": "Nee",
    "aantal_kindplaatsen": 50,
    "status": "Ingeschreven",
    "inschrijfdatum": "27-07-2012",
    "opvanglocatie_postcode": "8312AW",
    "opvanglocatie_woonplaats": "Creil",
    "kvk_nummer_houder": "64247465",
    "vestigingsnummer_houder": "000005206480",
    "rechtsvorm_houder": "VennootschapOnderFirma",
    "start_geschillencommissie": "2016-03-14",
    "cbs_code": "171",
    "verantwoordelijke_gemeente": "Noordoostpolder",
    "lrk_url": "https://www.landelijkregisterkinderopvang.nl/pp/#/inzien/oko/gegevens/88d91903-e1d7-4817-9f21-6697fc23f7d5"
}
