{
    "lrk_id": "107153075",
    "type_oko": "VGO",
    "opc": "Nee",
    "actuele_naam_oko": "Hertog-Stam",
    "aantal_kindplaatsen": 5,
    "status": "Uitgeschreven",
    "inschrijfdatum": "29-11-2010",
    "uitschrijfdatum": "31-07-2020",
    "opvanglocatie_adres": "Vlietenburg 5 ",
    "opvanglocatie_postcode": "2804WP",
    "opvanglocatie_woonplaats": "Gouda",
    "bag_id": "0513010013058477",
    "naam_houder": "Hertog-Stam",
    "contact_telefoon": "''",
    "cbs_code": "513",
    "verantwoordelijke_gemeente": "Gouda",
    "lrk_url": "https://www.landelijkregisterkinderopvang.nl/pp/#/inzien/oko/gegevens/c0bb6d0d-044f-4f34-9d05-ae57741d8f85"
}
