{
    "lrk_id": "118602603",
    "type_oko": "VGO",
    "opc": "Nee",
    "actuele_naam_oko": "de Ridder-van Londen",
    "aantal_kindplaatsen": 4,
    "status": "Uitgeschreven",
    "inschrijfdatum": "16-11-2010",
    "uitschrijfdatum": "01-08-2024",
    "opvanglocatie_adres": "Plataanstraat 2 ",
    "opvanglocatie_postcode": "6823JK",
    "opvanglocatie_woonplaats": "Arnhem",
    "bag_id": "0202010000295355",
    "naam_houder": "de Ridder-van Londen",
    "contact_telefoon": "''",
    "cbs_code": "202",
    "verantwoordelijke_gemeente": "Arnhem",
    "lrk_url": "https://www.landelijkregisterkinderopvang.nl/pp/#/inzien/oko/gegevens/79681fb0-8c91-4ca4-bd20-9594ccd54835"
}
