{
    "lrk_id": "118808175",
    "type_oko": "VGO",
    "opc": "Nee",
    "aantal_kindplaatsen": 6,
    "status": "Uitgeschreven",
    "inschrijfdatum": "07-05-2015",
    "uitschrijfdatum": "04-10-2022",
    "opvanglocatie_woonplaats": "Opvang bij de vraagouder",
    "cbs_code": "851",
    "verantwoordelijke_gemeente": "Steenbergen",
    "gastouderbureau_1": "146575891",
    "lrk_url": "https://www.landelijkregisterkinderopvang.nl/pp/#/inzien/oko/gegevens/0dd035bd-0688-4b89-b37d-d234a198a4a4"
}
