{
    "lrk_id": "130206362",
    "type_oko": "VGO",
    "opc": "Nee",
    "aantal_kindplaatsen": 6,
    "status": "Uitgeschreven",
    "inschrijfdatum": "13-01-2014",
    "uitschrijfdatum": "01-09-2024",
    "opvanglocatie_woonplaats": "Opvang bij de vraagouder",
    "cbs_code": "1960",
    "verantwoordelijke_gemeente": "West Betuwe",
    "gastouderbureau_1": "192754063",
    "lrk_url": "https://www.landelijkregisterkinderopvang.nl/pp/#/inzien/oko/gegevens/a5d9346e-ee4f-4b6a-90ce-6199f78d21f9"
}
