{
    "lrk_id": "131830879",
    "type_oko": "BSO",
    "opc": "Nee",
    "aantal_kindplaatsen": 75,
    "status": "Ingeschreven",
    "inschrijfdatum": "07-01-2014",
    "opvanglocatie_postcode": "4841XC",
    "opvanglocatie_woonplaats": "Prinsenbeek",
    "kvk_nummer_houder": "20125402",
    "vestigingsnummer_houder": "000029950325",
    "rechtsvorm_houder": "Besloten Vennootschap",
    "start_geschillencommissie": "2016-01-10",
    "cbs_code": "758",
    "verantwoordelijke_gemeente": "Breda",
    "lrk_url": "https://www.landelijkregisterkinderopvang.nl/pp/#/inzien/oko/gegevens/f2a6e3ea-b3e7-4aae-93e9-6f38f44ded3a"
}
