{
    "lrk_id": "139186426",
    "type_oko": "BSO",
    "opc": "Nee",
    "aantal_kindplaatsen": 66,
    "status": "Ingeschreven",
    "inschrijfdatum": "13-08-2013",
    "opvanglocatie_postcode": "2983CL",
    "opvanglocatie_woonplaats": "Ridderkerk",
    "kvk_nummer_houder": "24428808",
    "vestigingsnummer_houder": "000035386711",
    "rechtsvorm_houder": "Besloten Vennootschap",
    "start_geschillencommissie": "2009-08-19",
    "cbs_code": "597",
    "verantwoordelijke_gemeente": "Ridderkerk",
    "lrk_url": "https://www.landelijkregisterkinderopvang.nl/pp/#/inzien/oko/gegevens/1823673e-89f1-4ee4-a21b-d733dc31ab7c"
}
