{
    "lrk_id": "139243331",
    "type_oko": "VGO",
    "opc": "Nee",
    "aantal_kindplaatsen": 6,
    "status": "Uitgeschreven",
    "inschrijfdatum": "22-11-2012",
    "uitschrijfdatum": "01-09-2018",
    "opvanglocatie_woonplaats": "Opvang bij de vraagouder",
    "cbs_code": "796",
    "verantwoordelijke_gemeente": "'s-Hertogenbosch",
    "gastouderbureau_1": "166040150",
    "lrk_url": "https://www.landelijkregisterkinderopvang.nl/pp/#/inzien/oko/gegevens/608b266c-6638-4f2a-bde5-ec23148f5a74"
}
