{
    "lrk_id": "140366751",
    "type_oko": "KDV",
    "opc": "Nee",
    "aantal_kindplaatsen": 32,
    "ve": "Ja",
    "status": "Ingeschreven",
    "inschrijfdatum": "15-08-2011",
    "opvanglocatie_postcode": "7041GL",
    "opvanglocatie_woonplaats": "'s-Heerenberg",
    "kvk_nummer_houder": "57468656",
    "vestigingsnummer_houder": "000036268496",
    "rechtsvorm_houder": "Besloten Vennootschap",
    "start_geschillencommissie": "2016-01-28",
    "cbs_code": "1955",
    "verantwoordelijke_gemeente": "Montferland",
    "lrk_url": "https://www.landelijkregisterkinderopvang.nl/pp/#/inzien/oko/gegevens/e98f8801-78f8-4f1a-a0fc-c973e5de2103"
}
