{
    "lrk_id": "141002451",
    "type_oko": "VGO",
    "opc": "Nee",
    "actuele_naam_oko": "Visser ten Napel",
    "aantal_kindplaatsen": 6,
    "status": "Ingeschreven",
    "inschrijfdatum": "30-09-2019",
    "opvanglocatie_adres": "Opvang bij de vraagouder",
    "naam_houder": "Visser ten Napel",
    "contact_telefoon": "''",
    "cbs_code": "184",
    "verantwoordelijke_gemeente": "Urk",
    "gastouderbureau_1": "187750154",
    "lrk_url": "https://www.landelijkregisterkinderopvang.nl/pp/#/inzien/oko/gegevens/2b4440b3-41d9-4ba9-894e-6cccd9142f35"
}
