{
    "lrk_id": "145127229",
    "type_oko": "VGO",
    "opc": "Nee",
    "aantal_kindplaatsen": 6,
    "status": "Uitgeschreven",
    "inschrijfdatum": "08-11-2010",
    "uitschrijfdatum": "11-08-2021",
    "opvanglocatie_postcode": "4882NP",
    "opvanglocatie_woonplaats": "Klein Zundert",
    "cbs_code": "879",
    "verantwoordelijke_gemeente": "Zundert",
    "gastouderbureau_1": "985438046",
    "lrk_url": "https://www.landelijkregisterkinderopvang.nl/pp/#/inzien/oko/gegevens/78a65431-c4b1-4f64-9b69-e042bbaebc3f"
}
