{
    "lrk_id": "145430583",
    "type_oko": "VGO",
    "opc": "Nee",
    "actuele_naam_oko": "Pauly-Wouters",
    "aantal_kindplaatsen": 6,
    "status": "Uitgeschreven",
    "inschrijfdatum": "15-10-2010",
    "uitschrijfdatum": "01-08-2018",
    "opvanglocatie_adres": "'t Zand 1 ",
    "opvanglocatie_postcode": "5571NK",
    "opvanglocatie_woonplaats": "Bergeijk",
    "bag_id": "1724010000005931",
    "naam_houder": "Pauly-Wouters",
    "contact_telefoon": "''",
    "cbs_code": "1724",
    "verantwoordelijke_gemeente": "Bergeijk",
    "lrk_url": "https://www.landelijkregisterkinderopvang.nl/pp/#/inzien/oko/gegevens/77f0eb89-e7d8-4af6-a542-85e67e10f029"
}
