{
    "lrk_id": "148847717",
    "type_oko": "BSO",
    "opc": "Nee",
    "aantal_kindplaatsen": 34,
    "status": "Uitgeschreven",
    "inschrijfdatum": "09-12-2019",
    "uitschrijfdatum": "23-12-2023",
    "opvanglocatie_postcode": "3071AG",
    "opvanglocatie_woonplaats": "Rotterdam",
    "kvk_nummer_houder": "30278497",
    "cbs_code": "599",
    "verantwoordelijke_gemeente": "Rotterdam",
    "lrk_url": "https://www.landelijkregisterkinderopvang.nl/pp/#/inzien/oko/gegevens/bc2e0323-fbbe-4556-9e8d-86634bf29046"
}
