{
    "lrk_id": "150232202",
    "type_oko": "VGO",
    "opc": "Nee",
    "actuele_naam_oko": "Waterschoot-van Loon",
    "aantal_kindplaatsen": 6,
    "status": "Uitgeschreven",
    "inschrijfdatum": "17-08-2012",
    "uitschrijfdatum": "03-10-2018",
    "opvanglocatie_adres": "Zeegstraat 46 ",
    "opvanglocatie_postcode": "5541EX",
    "opvanglocatie_woonplaats": "Reusel",
    "bag_id": "1667010000002482",
    "naam_houder": "Waterschoot-van Loon",
    "contact_telefoon": "''",
    "cbs_code": "1667",
    "verantwoordelijke_gemeente": "Reusel-De Mierden",
    "lrk_url": "https://www.landelijkregisterkinderopvang.nl/pp/#/inzien/oko/gegevens/a3c89875-a87c-4889-ac93-8b9ce862e2e6"
}
