{
    "lrk_id": "150397525",
    "type_oko": "GOB",
    "opc": "Nee",
    "status": "Ingeschreven",
    "inschrijfdatum": "01-01-2010",
    "opvanglocatie_postcode": "1687AL",
    "opvanglocatie_woonplaats": "Wognum",
    "kvk_nummer_houder": "37127943",
    "vestigingsnummer_houder": "000014659891",
    "rechtsvorm_houder": "Besloten Vennootschap",
    "start_geschillencommissie": "2016-01-29",
    "cbs_code": "420",
    "verantwoordelijke_gemeente": "Medemblik",
    "lrk_url": "https://www.landelijkregisterkinderopvang.nl/pp/#/inzien/oko/gegevens/00d953e9-5b88-430c-baea-32c5f61bc5ac"
}
