{
    "lrk_id": "156683027",
    "type_oko": "VGO",
    "opc": "Nee",
    "actuele_naam_oko": "Witsenburg ev Van Iterson",
    "aantal_kindplaatsen": 6,
    "status": "Uitgeschreven",
    "inschrijfdatum": "11-04-2011",
    "uitschrijfdatum": "01-01-2018",
    "opvanglocatie_adres": "Pal Maleterstraat 7 ",
    "opvanglocatie_postcode": "2332ZG",
    "opvanglocatie_woonplaats": "Leiden",
    "bag_id": "0546010000051763",
    "naam_houder": "Witsenburg ev Van Iterson",
    "contact_telefoon": "''",
    "cbs_code": "546",
    "verantwoordelijke_gemeente": "Leiden",
    "lrk_url": "https://www.landelijkregisterkinderopvang.nl/pp/#/inzien/oko/gegevens/a4960e89-00b8-49f8-8733-776890cbd372"
}
