{
    "lrk_id": "158857203",
    "type_oko": "VGO",
    "opc": "Nee",
    "aantal_kindplaatsen": 6,
    "status": "Uitgeschreven",
    "inschrijfdatum": "22-08-2022",
    "uitschrijfdatum": "31-03-2024",
    "opvanglocatie_woonplaats": "Opvang bij de vraagouder",
    "cbs_code": "1581",
    "verantwoordelijke_gemeente": "Utrechtse Heuvelrug",
    "gastouderbureau_1": "201268061",
    "lrk_url": "https://www.landelijkregisterkinderopvang.nl/pp/#/inzien/oko/gegevens/9a981011-9cd9-43d2-abdf-30352494913d"
}
