{
    "lrk_id": "161655452",
    "type_oko": "VGO",
    "opc": "Nee",
    "actuele_naam_oko": "Ouardani",
    "aantal_kindplaatsen": 6,
    "status": "Uitgeschreven",
    "inschrijfdatum": "30-06-2021",
    "uitschrijfdatum": "24-02-2023",
    "opvanglocatie_adres": "Opvang bij de vraagouder",
    "naam_houder": "Ouardani",
    "contact_telefoon": "''",
    "cbs_code": "599",
    "verantwoordelijke_gemeente": "Rotterdam",
    "lrk_url": "https://www.landelijkregisterkinderopvang.nl/pp/#/inzien/oko/gegevens/39b0d829-8449-4cfe-ae66-032867b4bd8d"
}
