{
    "lrk_id": "164591485",
    "type_oko": "KDV",
    "opc": "Nee",
    "actuele_naam_oko": "Montessorigroep ZieZo 0-4",
    "aantal_kindplaatsen": 16,
    "ve": "Nee",
    "status": "Uitgeschreven",
    "inschrijfdatum": "29-08-2018",
    "uitschrijfdatum": "04-09-2023",
    "opvanglocatie_adres": "'t Zand 2 ",
    "opvanglocatie_postcode": "4707VX",
    "opvanglocatie_woonplaats": "Roosendaal",
    "bag_id": "1674010000503445",
    "naam_houder": "Kreukelz",
    "kvk_nummer_houder": "65998464",
    "vestigingsnummer_houder": "000039955923",
    "houder_adres": "Zundertseweg 17 ",
    "houder_postcode": "4707XD",
    "houder_woonplaats": "Roosendaal",
    "correspondentie_adres": "Flintdijk 23 ",
    "correspondentie_postcode": "4706JX",
    "correspondentie_woonplaats": "Roosendaal",
    "contact_persoon": "Miranda van der Star",
    "contact_telefoon": "'06-25112373'",
    "contact_emailadres": "info@kreukelz.nl",
    "cbs_code": "1674",
    "verantwoordelijke_gemeente": "Roosendaal",
    "lrk_url": "https://www.landelijkregisterkinderopvang.nl/pp/#/inzien/oko/gegevens/233a3d5c-40c5-4b98-b6e0-5fad04a57cbf"
}
