{
    "lrk_id": "169364902",
    "type_oko": "VGO",
    "opc": "Nee",
    "aantal_kindplaatsen": 4,
    "status": "Uitgeschreven",
    "inschrijfdatum": "05-12-2016",
    "uitschrijfdatum": "01-08-2024",
    "opvanglocatie_woonplaats": "Opvang bij de vraagouder",
    "cbs_code": "845",
    "verantwoordelijke_gemeente": "Sint-Michielsgestel",
    "gastouderbureau_1": "208914973",
    "lrk_url": "https://www.landelijkregisterkinderopvang.nl/pp/#/inzien/oko/gegevens/10571873-c3b5-432e-9f31-97bf4761c2b2"
}
