{
    "lrk_id": "175040874",
    "type_oko": "VGO",
    "opc": "Nee",
    "aantal_kindplaatsen": 4,
    "status": "Uitgeschreven",
    "inschrijfdatum": "01-12-2010",
    "uitschrijfdatum": "20-03-2018",
    "opvanglocatie_postcode": "2914BZ",
    "opvanglocatie_woonplaats": "Nieuwerkerk aan den IJssel",
    "cbs_code": "1892",
    "verantwoordelijke_gemeente": "Zuidplas",
    "gastouderbureau_1": "823783145",
    "lrk_url": "https://www.landelijkregisterkinderopvang.nl/pp/#/inzien/oko/gegevens/45b469aa-c99a-4abc-9867-14419315ead1"
}
