{
    "lrk_id": "175994456",
    "type_oko": "VGO",
    "opc": "Nee",
    "actuele_naam_oko": "Blaak ten Brinke",
    "aantal_kindplaatsen": 6,
    "status": "Ingeschreven",
    "inschrijfdatum": "27-09-2021",
    "opvanglocatie_adres": "Prinses Margrietlaan 15 ",
    "opvanglocatie_postcode": "6986AP",
    "opvanglocatie_woonplaats": "Angerlo",
    "bag_id": "0299010000451932",
    "naam_houder": "Blaak ten Brinke",
    "contact_telefoon": "''",
    "cbs_code": "299",
    "verantwoordelijke_gemeente": "Zevenaar",
    "gastouderbureau_1": "163832341",
    "gastouderbureau_2": "210758855",
    "lrk_url": "https://www.landelijkregisterkinderopvang.nl/pp/#/inzien/oko/gegevens/b0bf2bfc-dd2c-4068-9803-e3ebff5df290"
}
