{
    "lrk_id": "180445765",
    "type_oko": "BSO",
    "opc": "Nee",
    "aantal_kindplaatsen": 28,
    "status": "Ingeschreven",
    "inschrijfdatum": "01-01-2010",
    "opvanglocatie_postcode": "2614GT",
    "opvanglocatie_woonplaats": "Delft",
    "kvk_nummer_houder": "95113886",
    "rechtsvorm_houder": "Besloten Vennootschap",
    "start_geschillencommissie": "2015-12-18",
    "cbs_code": "503",
    "verantwoordelijke_gemeente": "Delft",
    "lrk_url": "https://www.landelijkregisterkinderopvang.nl/pp/#/inzien/oko/gegevens/6cc8fb69-e414-445e-86c1-2edd32f87fb4"
}
