{
    "lrk_id": "181907665",
    "type_oko": "VGO",
    "opc": "Nee",
    "actuele_naam_oko": "Woude van der Meulen",
    "aantal_kindplaatsen": 6,
    "status": "Uitgeschreven",
    "inschrijfdatum": "18-03-2020",
    "uitschrijfdatum": "01-10-2021",
    "opvanglocatie_adres": "Oentzemastate 31 ",
    "opvanglocatie_postcode": "9298SE",
    "opvanglocatie_woonplaats": "Kollumersweach",
    "bag_id": "0079010000382393",
    "naam_houder": "Woude van der Meulen",
    "contact_telefoon": "''",
    "cbs_code": "1970",
    "verantwoordelijke_gemeente": "Noardeast-Fryslân",
    "lrk_url": "https://www.landelijkregisterkinderopvang.nl/pp/#/inzien/oko/gegevens/a5f082ce-254f-49ff-afb6-aeed9b2647f6"
}
