{
    "lrk_id": "185649889",
    "type_oko": "VGO",
    "opc": "Nee",
    "actuele_naam_oko": "Ploeg",
    "aantal_kindplaatsen": 6,
    "status": "Uitgeschreven",
    "inschrijfdatum": "18-02-2016",
    "uitschrijfdatum": "01-01-2024",
    "opvanglocatie_adres": "Lange Voor 39 ",
    "opvanglocatie_postcode": "8316BB",
    "opvanglocatie_woonplaats": "Marknesse",
    "bag_id": "0171010000029266",
    "naam_houder": "Ploeg",
    "contact_telefoon": "''",
    "cbs_code": "171",
    "verantwoordelijke_gemeente": "Noordoostpolder",
    "lrk_url": "https://www.landelijkregisterkinderopvang.nl/pp/#/inzien/oko/gegevens/ebdd569f-7ccb-4831-b65e-3bb7433c6e43"
}
