{
    "lrk_id": "192118079",
    "type_oko": "VGO",
    "opc": "Nee",
    "aantal_kindplaatsen": 6,
    "status": "Uitgeschreven",
    "inschrijfdatum": "23-04-2014",
    "uitschrijfdatum": "13-07-2018",
    "opvanglocatie_woonplaats": "Opvang bij de vraagouder",
    "cbs_code": "1969",
    "verantwoordelijke_gemeente": "Westerkwartier",
    "gastouderbureau_1": "150872628",
    "lrk_url": "https://www.landelijkregisterkinderopvang.nl/pp/#/inzien/oko/gegevens/c36aaa80-23e3-40fb-a92b-04b52ff738f4"
}
