{
    "lrk_id": "207437130",
    "type_oko": "KDV",
    "opc": "Nee",
    "actuele_naam_oko": "Stichting Christelijke Voorschool Eigenwijs",
    "aantal_kindplaatsen": 16,
    "ve": "Nee",
    "status": "Ingeschreven",
    "inschrijfdatum": "21-05-2012",
    "opvanglocatie_adres": "Kerkplein 2a ",
    "opvanglocatie_postcode": "5317JT",
    "opvanglocatie_woonplaats": "Nederhemert",
    "bag_id": "0297010000004431",
    "naam_houder": "Stichting Christelijke Voorschool Eigenwijs",
    "kvk_nummer_houder": "69924287",
    "vestigingsnummer_houder": "000069924287",
    "rechtsvorm_houder": "Onbekend",
    "start_geschillencommissie": "2015-12-09",
    "houder_adres": "Kerkplein 2a ",
    "houder_postcode": "5317JT",
    "houder_woonplaats": "Nederhemert",
    "correspondentie_adres": "Kerkplein 2a ",
    "correspondentie_postcode": "5317JT",
    "correspondentie_woonplaats": "Nederhemert",
    "contact_persoon": "W.C. van der Toorn",
    "contact_telefoon": "'0418-552280'",
    "contact_emailadres": "directie@wegwijzernederhemert.nl",
    "contact_website": "http://www.wegwijzernederhemert.nl",
    "cbs_code": "297",
    "verantwoordelijke_gemeente": "Zaltbommel",
    "lrk_url": "https://www.landelijkregisterkinderopvang.nl/pp/#/inzien/oko/gegevens/102a7186-e8a2-422f-ae44-db6ad941f9b9"
}
