{
    "lrk_id": "210376703",
    "type_oko": "VGO",
    "opc": "Nee",
    "aantal_kindplaatsen": 6,
    "status": "Uitgeschreven",
    "inschrijfdatum": "14-01-2014",
    "uitschrijfdatum": "13-04-2018",
    "opvanglocatie_woonplaats": "Opvang bij de vraagouder",
    "cbs_code": "163",
    "verantwoordelijke_gemeente": "Hellendoorn",
    "gastouderbureau_1": "124565372",
    "lrk_url": "https://www.landelijkregisterkinderopvang.nl/pp/#/inzien/oko/gegevens/d7146e24-ed29-4985-b2bd-03b4438aec2e"
}
