{
    "lrk_id": "210488347",
    "type_oko": "VGO",
    "opc": "Nee",
    "actuele_naam_oko": "Veldman",
    "aantal_kindplaatsen": 6,
    "status": "Uitgeschreven",
    "inschrijfdatum": "01-11-2011",
    "uitschrijfdatum": "01-07-2021",
    "opvanglocatie_adres": "Opvang bij de vraagouder",
    "naam_houder": "Veldman",
    "contact_telefoon": "''",
    "cbs_code": "1680",
    "verantwoordelijke_gemeente": "Aa en Hunze",
    "lrk_url": "https://www.landelijkregisterkinderopvang.nl/pp/#/inzien/oko/gegevens/c7b9554f-e4ba-4807-98f6-4a29f5ec2f15"
}
