{
    "lrk_id": "210594251",
    "type_oko": "VGO",
    "opc": "Nee",
    "actuele_naam_oko": "Mercelina",
    "aantal_kindplaatsen": 6,
    "status": "Uitgeschreven",
    "inschrijfdatum": "19-11-2015",
    "uitschrijfdatum": "18-01-2018",
    "opvanglocatie_adres": "Abadanstraat 59 ",
    "opvanglocatie_postcode": "3193AD",
    "opvanglocatie_woonplaats": "Hoogvliet Rotterdam",
    "bag_id": "0599010000277538",
    "naam_houder": "Mercelina",
    "contact_telefoon": "''",
    "cbs_code": "599",
    "verantwoordelijke_gemeente": "Rotterdam",
    "lrk_url": "https://www.landelijkregisterkinderopvang.nl/pp/#/inzien/oko/gegevens/4c88e87a-9580-4640-868f-d3fdebc95eb1"
}
