{
    "lrk_id": "214192702",
    "type_oko": "VGO",
    "opc": "Nee",
    "actuele_naam_oko": "Blom Focke",
    "aantal_kindplaatsen": 6,
    "status": "Uitgeschreven",
    "inschrijfdatum": "09-12-2016",
    "uitschrijfdatum": "04-10-2024",
    "opvanglocatie_adres": "Kapelaan Nausstraat 15 ",
    "opvanglocatie_postcode": "5348TH",
    "opvanglocatie_woonplaats": "Oss",
    "bag_id": "0828010001531118",
    "naam_houder": "Blom Focke",
    "contact_telefoon": "''",
    "cbs_code": "828",
    "verantwoordelijke_gemeente": "Oss",
    "lrk_url": "https://www.landelijkregisterkinderopvang.nl/pp/#/inzien/oko/gegevens/67300b89-c7cf-4787-9f4c-0b0aee243077"
}
