{
    "lrk_id": "224507229",
    "type_oko": "BSO",
    "opc": "Nee",
    "aantal_kindplaatsen": 22,
    "status": "Uitgeschreven",
    "inschrijfdatum": "09-11-2010",
    "uitschrijfdatum": "08-07-2025",
    "opvanglocatie_postcode": "8453XC",
    "opvanglocatie_woonplaats": "Oranjewoud",
    "kvk_nummer_houder": "01106502",
    "vestigingsnummer_houder": "000027967360",
    "cbs_code": "74",
    "verantwoordelijke_gemeente": "Heerenveen",
    "lrk_url": "https://www.landelijkregisterkinderopvang.nl/pp/#/inzien/oko/gegevens/a5d51cfe-9db9-4864-a319-a32633666d49"
}
