{
    "lrk_id": "229713555",
    "type_oko": "VGO",
    "opc": "Nee",
    "aantal_kindplaatsen": 6,
    "status": "Uitgeschreven",
    "inschrijfdatum": "30-09-2010",
    "uitschrijfdatum": "15-08-2024",
    "opvanglocatie_postcode": "5531LH",
    "opvanglocatie_woonplaats": "Bladel",
    "cbs_code": "1728",
    "verantwoordelijke_gemeente": "Bladel",
    "gastouderbureau_1": "476474085",
    "lrk_url": "https://www.landelijkregisterkinderopvang.nl/pp/#/inzien/oko/gegevens/114541cc-fb7d-45b4-8e98-34298c6d52a8"
}
