{
    "lrk_id": "232500769",
    "type_oko": "VGO",
    "opc": "Nee",
    "aantal_kindplaatsen": 6,
    "status": "Uitgeschreven",
    "inschrijfdatum": "22-05-2014",
    "uitschrijfdatum": "01-01-2021",
    "opvanglocatie_postcode": "5975CD",
    "opvanglocatie_woonplaats": "Sevenum",
    "cbs_code": "1507",
    "verantwoordelijke_gemeente": "Horst aan de Maas",
    "gastouderbureau_1": "220670067",
    "lrk_url": "https://www.landelijkregisterkinderopvang.nl/pp/#/inzien/oko/gegevens/fd3592b8-f0b0-4746-8e45-29f021d146f0"
}
