{
    "lrk_id": "233402275",
    "type_oko": "KDV",
    "opc": "Nee",
    "aantal_kindplaatsen": 11,
    "ve": "Ja",
    "status": "Uitgeschreven",
    "inschrijfdatum": "24-11-2016",
    "uitschrijfdatum": "04-08-2020",
    "opvanglocatie_postcode": "9648KK",
    "opvanglocatie_woonplaats": "Wildervank",
    "kvk_nummer_houder": "58840036",
    "vestigingsnummer_houder": "000031387349",
    "cbs_code": "47",
    "verantwoordelijke_gemeente": "Veendam",
    "lrk_url": "https://www.landelijkregisterkinderopvang.nl/pp/#/inzien/oko/gegevens/a9a1c6da-bb30-4234-a770-4bdb294de55c"
}
