{
    "lrk_id": "251654321",
    "type_oko": "VGO",
    "opc": "Nee",
    "aantal_kindplaatsen": 6,
    "status": "Uitgeschreven",
    "inschrijfdatum": "01-11-2016",
    "uitschrijfdatum": "01-06-2019",
    "opvanglocatie_postcode": "4566AN",
    "opvanglocatie_woonplaats": "Heikant",
    "cbs_code": "677",
    "verantwoordelijke_gemeente": "Hulst",
    "gastouderbureau_1": "296625346",
    "lrk_url": "https://www.landelijkregisterkinderopvang.nl/pp/#/inzien/oko/gegevens/43dbfef4-a71a-475d-b0f8-8a94d6527595"
}
