{
    "lrk_id": "258901858",
    "type_oko": "BSO",
    "opc": "Nee",
    "aantal_kindplaatsen": 60,
    "status": "Ingeschreven",
    "inschrijfdatum": "01-01-2010",
    "opvanglocatie_postcode": "2613VX",
    "opvanglocatie_woonplaats": "Delft",
    "kvk_nummer_houder": "53182561",
    "rechtsvorm_houder": "BV",
    "start_geschillencommissie": "2016-04-06",
    "cbs_code": "503",
    "verantwoordelijke_gemeente": "Delft",
    "lrk_url": "https://www.landelijkregisterkinderopvang.nl/pp/#/inzien/oko/gegevens/cba2dca3-e02e-4b00-af28-3a0e88138bff"
}
