{
    "lrk_id": "272930635",
    "type_oko": "KDV",
    "opc": "Nee",
    "actuele_naam_oko": "De peutertuin",
    "aantal_kindplaatsen": 16,
    "ve": "Nee",
    "status": "Ingeschreven",
    "inschrijfdatum": "01-09-2025",
    "opvanglocatie_adres": "Anthuriumsingel 148 ",
    "opvanglocatie_postcode": "2651NZ",
    "opvanglocatie_woonplaats": "Berkel en Rodenrijs",
    "bag_id": "1621010000024337",
    "naam_houder": "De Paddestoel B.V.",
    "kvk_nummer_houder": "96716789",
    "vestigingsnummer_houder": "000042597196",
    "rechtsvorm_houder": "Besloten Vennootschap",
    "start_geschillencommissie": "2025-12-01",
    "houder_adres": "Postbus 275",
    "houder_postcode": "2650AG",
    "houder_woonplaats": "Berkel en Rodenrijs",
    "correspondentie_adres": "Naardermeerstraat 151 ",
    "correspondentie_postcode": "2652JH",
    "correspondentie_woonplaats": "Berkel en Rodenrijs",
    "contact_persoon": "C.M.M. Verhulst",
    "contact_telefoon": "'0105199337'",
    "contact_emailadres": "yvonne.verhulst@de-paddestoel.nl",
    "contact_website": "http://www.de-paddestoel.nl",
    "cbs_code": "1621",
    "verantwoordelijke_gemeente": "Lansingerland",
    "lrk_url": "https://www.landelijkregisterkinderopvang.nl/pp/#/inzien/oko/gegevens/30c46f4b-0b38-4824-8ab6-e02b48aef05f"
}
