{
    "lrk_id": "279220492",
    "type_oko": "BSO",
    "opc": "Nee",
    "aantal_kindplaatsen": 40,
    "status": "Ingeschreven",
    "inschrijfdatum": "01-01-2019",
    "opvanglocatie_postcode": "7441GZ",
    "opvanglocatie_woonplaats": "Nijverdal",
    "kvk_nummer_houder": "08106503",
    "vestigingsnummer_houder": "000042819695",
    "rechtsvorm_houder": "Besloten Vennootschap",
    "start_geschillencommissie": "2015-12-28",
    "cbs_code": "163",
    "verantwoordelijke_gemeente": "Hellendoorn",
    "lrk_url": "https://www.landelijkregisterkinderopvang.nl/pp/#/inzien/oko/gegevens/9ae3e66d-6e32-4a72-8ba5-93a1cff23669"
}
