{
    "lrk_id": "288934155",
    "type_oko": "BSO",
    "opc": "Nee",
    "actuele_naam_oko": "Kind aan Zee",
    "aantal_kindplaatsen": 22,
    "status": "Ingeschreven",
    "inschrijfdatum": "04-05-2018",
    "opvanglocatie_adres": "Neptunusstraat 76 ",
    "opvanglocatie_postcode": "2586GT",
    "opvanglocatie_woonplaats": "'s-Gravenhage",
    "bag_id": "0518010001761885",
    "naam_houder": "Kind aan Zee B.V.",
    "kvk_nummer_houder": "70555478",
    "vestigingsnummer_houder": "000038811545",
    "rechtsvorm_houder": "BeslotenVennootschap",
    "start_geschillencommissie": "2018-02-02",
    "houder_adres": "Katwijkstraat 23 ",
    "houder_postcode": "2586VK",
    "houder_woonplaats": "'s-Gravenhage",
    "correspondentie_adres": "Neptunusstraat 76 ",
    "correspondentie_postcode": "2586GT",
    "correspondentie_woonplaats": "'s-Gravenhage",
    "contact_persoon": "N. Demenint",
    "contact_telefoon": "'06-41377665'",
    "contact_emailadres": "kindaanzee@gmail.com",
    "cbs_code": "518",
    "verantwoordelijke_gemeente": "'s-Gravenhage",
    "lrk_url": "https://www.landelijkregisterkinderopvang.nl/pp/#/inzien/oko/gegevens/317d9e74-f867-4915-9512-425748eed5d4"
}
