{
    "lrk_id": "293530932",
    "type_oko": "KDV",
    "opc": "Nee",
    "actuele_naam_oko": "Doomijn Peuterspeelzaal Nieuwstraat 17",
    "aantal_kindplaatsen": 16,
    "ve": "Ja",
    "status": "Uitgeschreven",
    "inschrijfdatum": "01-10-2017",
    "uitschrijfdatum": "01-01-2020",
    "opvanglocatie_adres": "Nieuwstraat 17 ",
    "opvanglocatie_postcode": "7927PJ",
    "opvanglocatie_woonplaats": "Alteveer",
    "bag_id": "1690010000006465",
    "naam_houder": "Stichting Doomijn Peuterspeelzalen",
    "kvk_nummer_houder": "59356782",
    "vestigingsnummer_houder": "000032480555",
    "houder_adres": "Postbus 1064",
    "houder_postcode": "8001BB",
    "houder_woonplaats": "Zwolle",
    "correspondentie_adres": "Burgemeester Drijbersingel 11 ",
    "correspondentie_postcode": "8021DA",
    "correspondentie_woonplaats": "Zwolle",
    "contact_persoon": "mevrouw Sandra Pit",
    "contact_telefoon": "'0683331303'",
    "contact_emailadres": "s.pit@doomijn.nl",
    "contact_website": "http://www.doomijn.nl",
    "cbs_code": "1690",
    "verantwoordelijke_gemeente": "De Wolden",
    "lrk_url": "https://www.landelijkregisterkinderopvang.nl/pp/#/inzien/oko/gegevens/e832b0e5-0969-49ab-af1a-5be1c370eacd"
}
