{
    "lrk_id": "308406084",
    "type_oko": "KDV",
    "opc": "Nee",
    "actuele_naam_oko": "PSZ 't Groene eiland",
    "aantal_kindplaatsen": 32,
    "ve": "Ja",
    "status": "Uitgeschreven",
    "inschrijfdatum": "09-11-2016",
    "uitschrijfdatum": "01-01-2019",
    "opvanglocatie_adres": "Deltaweg 105 ",
    "opvanglocatie_postcode": "2134XS",
    "opvanglocatie_woonplaats": "Hoofddorp",
    "bag_id": "0394010000319737",
    "naam_houder": "Stichting Kinderopvang Haarlemmermeer",
    "kvk_nummer_houder": "41223014",
    "vestigingsnummer_houder": "000025484397",
    "houder_adres": "Marktplein 47 ",
    "houder_postcode": "2132DA",
    "houder_woonplaats": "Hoofddorp",
    "contact_telefoon": "'023-5672020'",
    "contact_emailadres": "info@kinderopvanghaarlemmermeer.nl",
    "contact_website": "http://www.kinderopvanghaarlemmermeer.nl",
    "cbs_code": "394",
    "verantwoordelijke_gemeente": "Haarlemmermeer",
    "lrk_url": "https://www.landelijkregisterkinderopvang.nl/pp/#/inzien/oko/gegevens/9daad7c7-9095-4ee2-828f-7a206641264b"
}
