{
    "lrk_id": "312569944",
    "type_oko": "BSO",
    "opc": "Nee",
    "aantal_kindplaatsen": 24,
    "status": "Ingeschreven",
    "inschrijfdatum": "17-04-2025",
    "opvanglocatie_postcode": "8064DJ",
    "opvanglocatie_woonplaats": "Zwartsluis",
    "kvk_nummer_houder": "41022509",
    "rechtsvorm_houder": "Stichting",
    "start_geschillencommissie": "2016-04-20",
    "cbs_code": "1896",
    "verantwoordelijke_gemeente": "Zwartewaterland",
    "lrk_url": "https://www.landelijkregisterkinderopvang.nl/pp/#/inzien/oko/gegevens/a1345e1d-945f-46f2-8bc2-4abbf253808e"
}
