{
    "lrk_id": "330456349",
    "type_oko": "BSO",
    "opc": "Nee",
    "actuele_naam_oko": "Vrom en tom",
    "aantal_kindplaatsen": 98,
    "status": "Ingeschreven",
    "inschrijfdatum": "01-01-2010",
    "opvanglocatie_adres": "Rousseaulaan 8 ",
    "opvanglocatie_postcode": "1277CH",
    "opvanglocatie_woonplaats": "Huizen",
    "bag_id": "0406010000049003",
    "naam_houder": "Stichting Kinderopvang Huizen",
    "kvk_nummer_houder": "41193172",
    "vestigingsnummer_houder": "000000067253",
    "rechtsvorm_houder": "Stichting",
    "start_geschillencommissie": "2015-12-23",
    "houder_adres": "Postbus 3060",
    "houder_postcode": "1270EB",
    "houder_woonplaats": "Huizen",
    "correspondentie_adres": "Postbus 3060",
    "correspondentie_postcode": "1270EB",
    "correspondentie_woonplaats": "HUIZEN",
    "contact_persoon": "Simone Horst",
    "contact_telefoon": "'0357200300'",
    "contact_emailadres": "info@kinderopvanghuizen.nl",
    "contact_website": "http://www.kinderopvanghuizen.nl",
    "cbs_code": "406",
    "verantwoordelijke_gemeente": "Huizen",
    "lrk_url": "https://www.landelijkregisterkinderopvang.nl/pp/#/inzien/oko/gegevens/4a331664-c583-4aa6-9fb9-913b1cb6348e"
}
