{
    "lrk_id": "330836948",
    "type_oko": "BSO",
    "opc": "Nee",
    "aantal_kindplaatsen": 22,
    "status": "Ingeschreven",
    "inschrijfdatum": "01-06-2024",
    "opvanglocatie_postcode": "6665DH",
    "opvanglocatie_woonplaats": "Driel",
    "kvk_nummer_houder": "73228397",
    "vestigingsnummer_houder": "000041287614",
    "rechtsvorm_houder": "Eenmanszaak",
    "start_geschillencommissie": "2023-01-01",
    "cbs_code": "1734",
    "verantwoordelijke_gemeente": "Overbetuwe",
    "lrk_url": "https://www.landelijkregisterkinderopvang.nl/pp/#/inzien/oko/gegevens/3c9699c6-c4bb-4aab-9540-aebdf53418d1"
}
