{
    "lrk_id": "357439648",
    "type_oko": "KDV",
    "opc": "Nee",
    "aantal_kindplaatsen": 80,
    "ve": "Nee",
    "status": "Ingeschreven",
    "inschrijfdatum": "23-05-2016",
    "opvanglocatie_postcode": "1079VW",
    "opvanglocatie_woonplaats": "Amsterdam",
    "kvk_nummer_houder": "65016084",
    "vestigingsnummer_houder": "000033777268",
    "rechtsvorm_houder": "Besloten Vennootschap",
    "start_geschillencommissie": "2016-04-18",
    "cbs_code": "363",
    "verantwoordelijke_gemeente": "Amsterdam",
    "lrk_url": "https://www.landelijkregisterkinderopvang.nl/pp/#/inzien/oko/gegevens/9f027916-ad57-4308-aaf2-099a0388f649"
}
