{
    "lrk_id": "416067244",
    "type_oko": "KDV",
    "opc": "Nee",
    "aantal_kindplaatsen": 13,
    "ve": "Ja",
    "status": "Uitgeschreven",
    "inschrijfdatum": "01-01-2014",
    "uitschrijfdatum": "08-02-2018",
    "opvanglocatie_postcode": "7765BG",
    "opvanglocatie_woonplaats": "Weiteveen",
    "kvk_nummer_houder": "58840036",
    "vestigingsnummer_houder": "000027483746",
    "cbs_code": "114",
    "verantwoordelijke_gemeente": "Emmen",
    "lrk_url": "https://www.landelijkregisterkinderopvang.nl/pp/#/inzien/oko/gegevens/1f715569-a326-4e32-a209-32a0e6eb6754"
}
