{
    "lrk_id": "433835023",
    "type_oko": "BSO",
    "opc": "Nee",
    "aantal_kindplaatsen": 60,
    "status": "Ingeschreven",
    "inschrijfdatum": "01-08-2007",
    "opvanglocatie_postcode": "6031HR",
    "opvanglocatie_woonplaats": "Nederweert",
    "kvk_nummer_houder": "14119365",
    "vestigingsnummer_houder": "000014119365",
    "rechtsvorm_houder": "Stichting",
    "start_geschillencommissie": "2016-01-21",
    "cbs_code": "946",
    "verantwoordelijke_gemeente": "Nederweert",
    "lrk_url": "https://www.landelijkregisterkinderopvang.nl/pp/#/inzien/oko/gegevens/5f9bf07f-4539-4adc-bd6c-9f847079175f"
}
