{
    "lrk_id": "469642117",
    "type_oko": "KDV",
    "opc": "Nee",
    "aantal_kindplaatsen": 67,
    "ve": "Nee",
    "status": "Ingeschreven",
    "inschrijfdatum": "01-01-2010",
    "opvanglocatie_postcode": "1056TP",
    "opvanglocatie_woonplaats": "Amsterdam",
    "kvk_nummer_houder": "34182150",
    "vestigingsnummer_houder": "000015840190",
    "rechtsvorm_houder": "BV",
    "start_geschillencommissie": "2015-12-29",
    "cbs_code": "363",
    "verantwoordelijke_gemeente": "Amsterdam",
    "lrk_url": "https://www.landelijkregisterkinderopvang.nl/pp/#/inzien/oko/gegevens/1b680cd3-12a5-45b9-8177-328ef7547c31"
}
