{
    "lrk_id": "485572412",
    "type_oko": "VGO",
    "opc": "Nee",
    "actuele_naam_oko": "Ligthart Koster",
    "aantal_kindplaatsen": 6,
    "status": "Uitgeschreven",
    "inschrijfdatum": "20-12-2022",
    "uitschrijfdatum": "31-10-2024",
    "opvanglocatie_adres": "Kleine Immert 10 ",
    "opvanglocatie_postcode": "1616RC",
    "opvanglocatie_woonplaats": "Hoogkarspel",
    "bag_id": "0498010000005439",
    "naam_houder": "Ligthart Koster",
    "contact_persoon": "Mevrouw L.E.M. Ligthart-Koster",
    "contact_telefoon": "''",
    "contact_emailadres": "lisa_koster@hotmail.com",
    "cbs_code": "498",
    "verantwoordelijke_gemeente": "Drechterland",
    "lrk_url": "https://www.landelijkregisterkinderopvang.nl/pp/#/inzien/oko/gegevens/4b0a58d5-034d-4a03-bd0c-55c172779ace"
}
