{
    "lrk_id": "541281203",
    "type_oko": "BSO",
    "opc": "Nee",
    "actuele_naam_oko": "BSO De Toermalijn",
    "aantal_kindplaatsen": 30,
    "status": "Uitgeschreven",
    "inschrijfdatum": "18-08-2014",
    "uitschrijfdatum": "08-11-2022",
    "opvanglocatie_adres": "Tulpstraat 18 ",
    "opvanglocatie_postcode": "1521WB",
    "opvanglocatie_woonplaats": "Wormerveer",
    "bag_id": "0479010000041612",
    "naam_houder": "TintelTuin B.V.",
    "kvk_nummer_houder": "34327012",
    "vestigingsnummer_houder": "000026317524",
    "houder_adres": "Postbus 37117",
    "houder_postcode": "1030AC",
    "houder_woonplaats": "Amsterdam",
    "correspondentie_adres": "Tulpstraat 18 ",
    "correspondentie_postcode": "1521WB",
    "correspondentie_woonplaats": "Wormerveer",
    "contact_persoon": "Katrin Meijer",
    "contact_telefoon": "'0639113252'",
    "contact_emailadres": "k.meijer@tinteltuin.nl",
    "cbs_code": "479",
    "verantwoordelijke_gemeente": "Zaanstad",
    "lrk_url": "https://www.landelijkregisterkinderopvang.nl/pp/#/inzien/oko/gegevens/8f1e079a-bf78-4905-957c-217bda6a52a9"
}
