{
    "lrk_id": "543648709",
    "type_oko": "GOB",
    "opc": "Nee",
    "status": "Uitgeschreven",
    "inschrijfdatum": "19-06-2014",
    "uitschrijfdatum": "16-09-2024",
    "opvanglocatie_postcode": "6825ME",
    "opvanglocatie_woonplaats": "Arnhem",
    "kvk_nummer_houder": "60389702",
    "vestigingsnummer_houder": "000060389702",
    "cbs_code": "202",
    "verantwoordelijke_gemeente": "Arnhem",
    "lrk_url": "https://www.landelijkregisterkinderopvang.nl/pp/#/inzien/oko/gegevens/1bd01602-10a5-492d-982c-ebc6273107de"
}
