{
    "lrk_id": "554129012",
    "type_oko": "VGO",
    "opc": "Nee",
    "actuele_naam_oko": "Eenstroom",
    "aantal_kindplaatsen": 6,
    "status": "Ingeschreven",
    "inschrijfdatum": "28-08-2025",
    "opvanglocatie_adres": "Ooipoortstraat 71 ",
    "opvanglocatie_postcode": "6981DT",
    "opvanglocatie_woonplaats": "Doesburg",
    "bag_id": "0221010000324136",
    "naam_houder": "Eenstroom",
    "contact_telefoon": "''",
    "cbs_code": "221",
    "verantwoordelijke_gemeente": "Doesburg",
    "gastouderbureau_1": "174815220",
    "lrk_url": "https://www.landelijkregisterkinderopvang.nl/pp/#/inzien/oko/gegevens/bae7d5fa-3b35-40f5-a990-827e02dadc64"
}
