{
    "lrk_id": "636097523",
    "type_oko": "VGO",
    "opc": "Nee",
    "actuele_naam_oko": "Goedegebuure Kroneman",
    "aantal_kindplaatsen": 6,
    "status": "Ingeschreven",
    "inschrijfdatum": "08-02-2019",
    "opvanglocatie_adres": "Tienhoven 110 ",
    "opvanglocatie_postcode": "4697GT",
    "opvanglocatie_woonplaats": "Sint-Annaland",
    "bag_id": "0716010000026579",
    "naam_houder": "Goedegebuure Kroneman",
    "contact_telefoon": "''",
    "cbs_code": "716",
    "verantwoordelijke_gemeente": "Tholen",
    "gastouderbureau_1": "144894154",
    "lrk_url": "https://www.landelijkregisterkinderopvang.nl/pp/#/inzien/oko/gegevens/410905dd-b976-4566-89f6-2479d0ac2f0e"
}
