{
    "lrk_id": "720388028",
    "type_oko": "BSO",
    "opc": "Nee",
    "aantal_kindplaatsen": 21,
    "status": "Uitgeschreven",
    "inschrijfdatum": "01-01-2010",
    "uitschrijfdatum": "01-10-2020",
    "opvanglocatie_postcode": "3371NA",
    "opvanglocatie_woonplaats": "Hardinxveld-Giessendam",
    "kvk_nummer_houder": "60901934",
    "cbs_code": "523",
    "verantwoordelijke_gemeente": "Hardinxveld-Giessendam",
    "lrk_url": "https://www.landelijkregisterkinderopvang.nl/pp/#/inzien/oko/gegevens/38dd4b49-6481-4f75-9e51-7008072430a1"
}
