{
    "lrk_id": "746238150",
    "type_oko": "VGO",
    "opc": "Nee",
    "aantal_kindplaatsen": 6,
    "status": "Uitgeschreven",
    "inschrijfdatum": "09-05-2016",
    "uitschrijfdatum": "23-01-2020",
    "opvanglocatie_woonplaats": "Opvang bij de vraagouder",
    "cbs_code": "1891",
    "verantwoordelijke_gemeente": "Dantumadiel",
    "gastouderbureau_1": "830987162",
    "lrk_url": "https://www.landelijkregisterkinderopvang.nl/pp/#/inzien/oko/gegevens/a53d3939-6d50-49ac-bd90-97cb58bf84bd"
}
