{
    "lrk_id": "761893556",
    "type_oko": "BSO",
    "opc": "Nee",
    "aantal_kindplaatsen": 18,
    "status": "Uitgeschreven",
    "inschrijfdatum": "21-10-2019",
    "uitschrijfdatum": "01-12-2021",
    "opvanglocatie_postcode": "4455AT",
    "opvanglocatie_woonplaats": "Nieuwdorp",
    "kvk_nummer_houder": "22049355",
    "cbs_code": "654",
    "verantwoordelijke_gemeente": "Borsele",
    "lrk_url": "https://www.landelijkregisterkinderopvang.nl/pp/#/inzien/oko/gegevens/40ca3279-d74d-44c0-9fec-1e37112fbe19"
}
