{
    "lrk_id": "942881515",
    "type_oko": "VGO",
    "opc": "Nee",
    "actuele_naam_oko": "Pot",
    "aantal_kindplaatsen": 6,
    "status": "Uitgeschreven",
    "inschrijfdatum": "01-11-2018",
    "uitschrijfdatum": "12-07-2019",
    "opvanglocatie_adres": "Opvang bij de vraagouder",
    "naam_houder": "Pot",
    "contact_telefoon": "''",
    "cbs_code": "482",
    "verantwoordelijke_gemeente": "Alblasserdam",
    "lrk_url": "https://www.landelijkregisterkinderopvang.nl/pp/#/inzien/oko/gegevens/d4bd4576-9995-4f19-b691-a1971a8c27a4"
}
