{
    "lrk_id": "952899528",
    "type_oko": "VGO",
    "opc": "Nee",
    "actuele_naam_oko": "N. Voortman",
    "aantal_kindplaatsen": 6,
    "status": "Uitgeschreven",
    "inschrijfdatum": "24-12-2020",
    "uitschrijfdatum": "01-05-2021",
    "opvanglocatie_adres": "Opvang bij de vraagouder",
    "naam_houder": "Voortman",
    "contact_telefoon": "''",
    "cbs_code": "405",
    "verantwoordelijke_gemeente": "Hoorn",
    "lrk_url": "https://www.landelijkregisterkinderopvang.nl/pp/#/inzien/oko/gegevens/88e18343-bf6c-4c22-8a91-8040ea880350"
}
